[
  {
    "Bezirksregierung": "BR Arnsberg",
    "Kreis": "Ennepe-Ruhr-Kreis",
    "Schulform": "Grundschule",
    "Schulnummer": "131209",
    "Schulname": "Witten, GG Bruch",
    "Index_25_26": "4",
    "Index_24_25": "4",
    "Difference": 0,
    "City": "Witten"
  },
  {
    "Bezirksregierung": "BR Arnsberg",
    "Kreis": "Ennepe-Ruhr-Kreis",
    "Schulform": "Grundschule",
    "Schulnummer": "131210",
    "Schulname": "Witten, GG Crengeldanzschule",
    "Index_25_26": "6",
    "Index_24_25": "6",
    "Difference": 0,
    "City": "Witten"
  },
  {
    "Bezirksregierung": "BR Arnsberg",
    "Kreis": "Ennepe-Ruhr-Kreis",
    "Schulform": "Grundschule",
    "Schulnummer": "131222",
    "Schulname": "Witten, GG Rüdinghauser",
    "Index_25_26": "2",
    "Index_24_25": "2",
    "Difference": 0,
    "City": "Witten"
  },
  {
    "Bezirksregierung": "BR Arnsberg",
    "Kreis": "Ennepe-Ruhr-Kreis",
    "Schulform": "Grundschule",
    "Schulnummer": "131234",
    "Schulname": "Witten, GG Dorfschule",
    "Index_25_26": "3",
    "Index_24_25": "3",
    "Difference": 0,
    "City": "Witten"
  },
  {
    "Bezirksregierung": "BR Arnsberg",
    "Kreis": "Ennepe-Ruhr-Kreis",
    "Schulform": "Grundschule",
    "Schulnummer": "131246",
    "Schulname": "Witten, GG Hellwegschule",
    "Index_25_26": "4",
    "Index_24_25": "4",
    "Difference": 0,
    "City": "Witten"
  },
  {
    "Bezirksregierung": "BR Arnsberg",
    "Kreis": "Ennepe-Ruhr-Kreis",
    "Schulform": "Grundschule",
    "Schulnummer": "131260",
    "Schulname": "Witten, GG Hüllbergschule",
    "Index_25_26": "3",
    "Index_24_25": "3",
    "Difference": 0,
    "City": "Witten",
    "lat": 51.4418069,
    "lon": 7.3854121
  },
  {
    "Bezirksregierung": "BR Arnsberg",
    "Kreis": "Ennepe-Ruhr-Kreis",
    "Schulform": "Grundschule",
    "Schulnummer": "131271",
    "Schulname": "Witten, GG Erlenschule",
    "Index_25_26": "6",
    "Index_24_25": "6",
    "Difference": 0,
    "City": "Witten"
  },
  {
    "Bezirksregierung": "BR Arnsberg",
    "Kreis": "Ennepe-Ruhr-Kreis",
    "Schulform": "Grundschule",
    "Schulnummer": "131283",
    "Schulname": "Witten, GG Harkort",
    "Index_25_26": "2",
    "Index_24_25": "2",
    "Difference": 0,
    "City": "Witten"
  },
  {
    "Bezirksregierung": "BR Arnsberg",
    "Kreis": "Ennepe-Ruhr-Kreis",
    "Schulform": "Grundschule",
    "Schulnummer": "131295",
    "Schulname": "Witten, GG Baedeker",
    "Index_25_26": "6",
    "Index_24_25": "6",
    "Difference": 0,
    "City": "Witten"
  },
  {
    "Bezirksregierung": "BR Arnsberg",
    "Kreis": "Ennepe-Ruhr-Kreis",
    "Schulform": "Grundschule",
    "Schulnummer": "131301",
    "Schulname": "Witten, GG Borbach",
    "Index_25_26": "1",
    "Index_24_25": "1",
    "Difference": 0,
    "City": "Witten"
  }
]